UVR_resources/__init__.py
UVR_resources/configs/Bandit/config_dnr_bandit_bsrnn_multi_mus64.yaml
UVR_resources/configs/Bandit/config_dnr_bandit_v2_mus64.yaml
UVR_resources/configs/MDX23C/config_dereverb_mdx23c.yaml
UVR_resources/configs/MDX23C/config_drumsep_mdx23c.yaml
UVR_resources/configs/MDX23C/config_mdx23c_similarity.yaml
UVR_resources/configs/MDX23C/model_2_stem_061321.yaml
UVR_resources/configs/MDX23C/model_2_stem_full_band_8k.yaml
UVR_resources/configs/Roformer/BandSplit/config_BandSplit-Roformer_FNO_by-Unwa.yaml
UVR_resources/configs/Roformer/BandSplit/config_BandSplit-Roformer_Karaoke_Frazer_by-becruily.yaml
UVR_resources/configs/Roformer/BandSplit/config_BandSplit-Roformer_Resurrection_Instrumental_by-Unwa.yaml
UVR_resources/configs/Roformer/BandSplit/config_BandSplit-Roformer_Resurrection_Vocals_by-Unwa.yaml
UVR_resources/configs/Roformer/BandSplit/config_BandSplit-Roformer_SW_by-jarredou.yaml
UVR_resources/configs/Roformer/BandSplit/config_BandSplit_Roformer_4stems_FT_by_SYH99999.yaml
UVR_resources/configs/Roformer/BandSplit/config_bs_roformer_chorus_male_female.yaml
UVR_resources/configs/Roformer/BandSplit/config_bs_roformer_deverb_8_384dim_10depth.yaml
UVR_resources/configs/Roformer/BandSplit/config_bs_roformer_ep_317_sdr_12.9755.yaml
UVR_resources/configs/Roformer/BandSplit/config_bs_roformer_ep_368_sdr_12.9628.yaml
UVR_resources/configs/Roformer/BandSplit/config_bs_roformer_ep_937_sdr_10.5309.yaml
UVR_resources/configs/Roformer/BandSplit/config_bs_roformer_inst_exp_vrl.yaml
UVR_resources/configs/Roformer/BandSplit/config_bs_roformer_revive_by_unwa.yaml
UVR_resources/configs/Roformer/BandSplit/config_bs_roformer_voc_gabox.yaml
UVR_resources/configs/Roformer/MelBand/config_MelBand-Roformer_BVE_by-Gonza.yaml
UVR_resources/configs/Roformer/MelBand/config_MelBand-Roformer_Duality_v1_by-Aname.yaml
UVR_resources/configs/Roformer/MelBand/config_MelBand-Roformer_Karaoke_Fusion_Total_by-Gonza.yaml
uvr_resources-1.21.0.dist-info/METADATA
uvr_resources-1.21.0.dist-info/WHEEL
uvr_resources-1.21.0.dist-info/licenses/LICENSE
uvr_resources-1.21.0.dist-info/RECORD
