Metadata-Version: 2.4
Name: UVR_resources
Version: 1.21.0
Summary: Package for UVR resources
License: MIT
License-File: LICENSE
Author: Politrees
Author-email: artyom.0.bebroy@gmail.com
Requires-Python: >=3.8
Classifier: License :: OSI Approved :: MIT License
Classifier: Programming Language :: Python :: 3
Classifier: Programming Language :: Python :: 3.8
Classifier: Programming Language :: Python :: 3.9
Classifier: Programming Language :: Python :: 3.10
Classifier: Programming Language :: Python :: 3.11
Classifier: Programming Language :: Python :: 3.12
Classifier: Programming Language :: Python :: 3.13
Classifier: Programming Language :: Python :: 3.14
Project-URL: Documentation, https://github.com/Politrees/UVR_resources/blob/main/README.md
Project-URL: Homepage, https://github.com/Politrees/UVR_resources
Project-URL: Repository, https://github.com/Politrees/UVR_resources
